top2/101903422.py
top2/__init__.py
Topsis_Shivanshu_101903422-0.0.1.dist-info/METADATA
Topsis_Shivanshu_101903422-0.0.1.dist-info/WHEEL
Topsis_Shivanshu_101903422-0.0.1.dist-info/top_level.txt
Topsis_Shivanshu_101903422-0.0.1.dist-info/RECORD
